pip_art/__init__.py
pip_art/main.py
pip_art/images/images.jpg
pip_art-0.1.5.dist-info/licenses/LICENSE
pip_art-0.1.5.dist-info/METADATA
pip_art-0.1.5.dist-info/WHEEL
pip_art-0.1.5.dist-info/entry_points.txt
pip_art-0.1.5.dist-info/top_level.txt
pip_art-0.1.5.dist-info/RECORD
