Metadata-Version: 2.4
Name: pip-art
Version: 0.1.5
Summary: Turn any long-running command into a visual delight!
Author-email: Timur <kk7629803@gmail.com>
Classifier: Programming Language :: Python :: 3
Classifier: License :: OSI Approved :: MIT License
Classifier: Operating System :: OS Independent
Requires-Python: >=3.9
License-File: LICENSE
Requires-Dist: term-image
Requires-Dist: rich
Requires-Dist: requests
Requires-Dist: toml
Dynamic: license-file
